[
    {
        "title": "The Nightingale",
        "gutenberg_id": 71096,
        "score": 4.24
    },
    {
        "title": "Wonder",
        "gutenberg_id": 27188,
        "score": 4.18
    },
    {
        "title": "The Martian",
        "gutenberg_id": 27400,
        "score": 4.17
    },
    {
        "title": "Pride and Prejudice",
        "gutenberg_id": 1342,
        "score": 4.14
    },
    {
        "title": "Winnie-the-Pooh (Winnie-the-Pooh, #1)",
        "gutenberg_id": 67098,
        "score": 4.12
    },
    {
        "title": "Anne of Green Gables (Anne of Green Gables, #1)",
        "gutenberg_id": 45,
        "score": 4.1
    },
    {
        "title": "The Velveteen Rabbit",
        "gutenberg_id": 11757,
        "score": 4.07
    },
    {
        "title": "The Lost Hero (The Heroes of Olympus, #1)",
        "gutenberg_id": 28059,
        "score": 4.06
    },
    {
        "title": "Les Misérables",
        "gutenberg_id": 135,
        "score": 4.04
    },
    {
        "title": "The Secret Garden",
        "gutenberg_id": 113,
        "score": 4.03
    },
    {
        "title": "A Little Princess",
        "gutenberg_id": 146,
        "score": 4.02
    },
    {
        "title": "The Importance of Being Earnest",
        "gutenberg_id": 844,
        "score": 4.01
    },
    {
        "title": "Jane Eyre",
        "gutenberg_id": 1260,
        "score": 4.0
    },
    {
        "title": "Persuasion",
        "gutenberg_id": 105,
        "score": 3.98
    },
    {
        "title": "Little Women (Little Women, #1)",
        "gutenberg_id": 514,
        "score": 3.97
    },
    {
        "title": "Peter Pan",
        "gutenberg_id": 16,
        "score": 3.96
    },
    {
        "title": "Stardust",
        "gutenberg_id": 9858,
        "score": 3.96
    },
    {
        "title": "Sense and Sensibility",
        "gutenberg_id": 161,
        "score": 3.95
    },
    {
        "title": "It",
        "gutenberg_id": 64009,
        "score": 3.95
    },
    {
        "title": "Alice's Adventures in Wonderland & Through the Looking-Glass",
        "gutenberg_id": 11,
        "score": 3.94
    }
]